django_admin_hstore_widget/__init__.py
django_admin_hstore_widget/forms.py
django_admin_hstore_widget/widgets.py
django_admin_hstore_widget/locale/ru/LC_MESSAGES/django.po
django_admin_hstore_widget/static/admin/js/django_admin_hstore_widget/django_admin_hstore_widget.js
django_admin_hstore_widget/static/admin/js/django_admin_hstore_widget/underscore-min.js
django_admin_hstore_widget/templates/django_admin_hstore_widget.html
tests/__init__.py
tests/models.py
tests/settings.py
tests/test_hstore_field.py
tests/urls.py
django_admin_hstore_widget-1.2.1.dist-info/LICENSE
django_admin_hstore_widget-1.2.1.dist-info/METADATA
django_admin_hstore_widget-1.2.1.dist-info/WHEEL
django_admin_hstore_widget-1.2.1.dist-info/top_level.txt
django_admin_hstore_widget-1.2.1.dist-info/RECORD
