Metadata-Version: 2.1
Name: django-admin-hstore-widget
Version: 1.2.1
Summary: Widget and Field to properly render HStore data in Django-Admin
Home-page: https://github.com/PokaInc/django-admin-hstore-widget
Author: Alexandre Dufour
Author-email: adufour@poka.io
Maintainer: Alexandre Dufour
Maintainer-email: adufour@poka.io
License: MIT
Keywords: django admin hstore render
Classifier: Development Status :: 5 - Production/Stable
Classifier: Environment :: Web Environment
Classifier: Intended Audience :: Developers
Classifier: License :: OSI Approved :: MIT License
Classifier: Operating System :: OS Independent
Classifier: Framework :: Django
Classifier: Framework :: Django :: 1.11
Classifier: Programming Language :: Python
Classifier: Programming Language :: Python :: 2
Classifier: Programming Language :: Python :: 2.7
Classifier: Programming Language :: Python :: 3
Classifier: Programming Language :: Python :: 3.4
Classifier: Programming Language :: Python :: 3.5
License-File: LICENSE
